osu_data_csv/__init__.py
osu_data_csv/conf.py
osu_data_csv/default_mapping.yaml
osu_data_csv/download.py
osu_data_csv/main.py
osu_data_csv/parse_sql.py
osu_data_csv/pipelines.py
osu_data_csv/tarbz2.py
osu_data_csv-0.1.6.dist-info/entry_points.txt
osu_data_csv-0.1.6.dist-info/METADATA
osu_data_csv-0.1.6.dist-info/WHEEL
osu_data_csv-0.1.6.dist-info/RECORD
