Metadata-Version: 2.1
Name: osu-data-csv
Version: 0.1.6
Summary: Downloads and Converts .sqls from data.ppy.sh into .csv
License: MIT
Author: Eve-ning
Author-email: dev_evening@hotmail.com
Requires-Python: >=3.8,<4.0
Classifier: License :: OSI Approved :: MIT License
Classifier: Programming Language :: Python :: 3
Classifier: Programming Language :: Python :: 3.8
Classifier: Programming Language :: Python :: 3.9
Classifier: Programming Language :: Python :: 3.10
Classifier: Programming Language :: Python :: 3.11
Requires-Dist: click (>=8.1.3,<9.0.0)
Requires-Dist: pandas (>=1.5.3,<2.0.0)
Requires-Dist: pyyaml (>=6.0,<7.0)
Requires-Dist: tqdm (>=4.64.1,<5.0.0)
Requires-Dist: wget (>=3.2,<4.0)
